feature_toggle_ui/__init__.py
feature_toggle_ui/feature_toggle_ui.py
integrations-0.0.2.dist-info/LICENSE
integrations-0.0.2.dist-info/METADATA
integrations-0.0.2.dist-info/WHEEL
integrations-0.0.2.dist-info/top_level.txt
integrations-0.0.2.dist-info/RECORD
